{
    "name": "Pyramid",
    "entities": [
        {
            "Entity": 0,
            "Tag": "",
            "components": [
                {
                    "type": "class TransformComponent",
                    "m_WorldTransformMatrix": {
                        "position": {
                            "x": -150.0,
                            "y": 100.0
                        },
                        "scale": {
                            "x": 1.0,
                            "y": 1.0
                        },
                        "rotation": 0.0
                    },
                    "m_LocalTransformMatrix": {
                        "position": {
                            "x": -150.0,
                            "y": 100.0
                        },
                        "scale": {
                            "x": 1.0,
                            "y": 1.0
                        },
                        "rotation": 0.0
                    },
                    "m_Entity": 0,
                    "m_IsActive": true,
                    "m_IsUnique": true,
                    "m_Id": 23
                },
                {
                    "type": "struct PyramidComponent",
                    "m_Entity": 0,
                    "m_IsActive": true,
                    "m_IsUnique": false,
                    "m_Id": 24
                }
            ],
            "children": []
        }
    ]
}